hydrogen_lambda/__init__.py
hydrogen_lambda/app.py
hydrogen_lambda/aws/__init__.py
hydrogen_lambda/aws/base.py
hydrogen_lambda/aws/sns.py
hydrogen_lambda/content.py
hydrogen_lambda/datadog/__init__.py
hydrogen_lambda/datadog/sns.py
hydrogen_lambda/datadog/utils.py
hydrogen_lambda/destination.py
hydrogen_lambda/errors.py
hydrogen_lambda-0.1.0.dist-info/WHEEL
hydrogen_lambda-0.1.0.dist-info/METADATA
hydrogen_lambda-0.1.0.dist-info/RECORD
