Metadata-Version: 2.1
Name: hydrogen-lambda
Version: 0.1.0
Summary: Get the message content from an input event
Author: nael.vindolet
Author-email: nael.vindolet@sewan.fr
Requires-Python: >=3.9.7,<4.0.0
Classifier: Programming Language :: Python :: 3
Classifier: Programming Language :: Python :: 3.10
Requires-Dist: pydantic (>=1.9.1,<2.0.0)
